marray/__init__.py
marray/_mask_text.py
marray/tests/test_marray.py
marray-0.0.12.dist-info/LICENSE
marray-0.0.12.dist-info/WHEEL
marray-0.0.12.dist-info/METADATA
marray-0.0.12.dist-info/RECORD
