Metadata-Version: 2.1
Name: marray
Version: 0.0.12
Summary: Masked versions of array API compatible arrays
Author-email: Matt Haberland <mhaberla@calpoly.edu>
Requires-Python: >=3.10
Classifier: License :: OSI Approved :: MIT License
Classifier: Programming Language :: Python :: 3.10
Classifier: Programming Language :: Python :: 3.11
Classifier: Programming Language :: Python :: 3.12
Classifier: Programming Language :: Python :: 3.13
Requires-Dist: jupyter-book ; extra == "docs"
Requires-Dist: ghp-import ; extra == "docs"
Requires-Dist: numpy ; extra == "test"
Requires-Dist: pytest ; extra == "test"
Requires-Dist: pytest-cov ; extra == "test"
Requires-Dist: array-api-strict ; extra == "test"
Requires-Dist: array-api-compat ; extra == "test"
Requires-Dist: pytorch ; extra == "test"
Project-URL: Home, https://github.com/mdhaber/marray
Provides-Extra: docs
Provides-Extra: test
